Workbook

Sheet ReadMe
A1: SOLIDARITY PROFILE ASSESSMENT TOOL
A2: ReadMe & Documentation
A4: ABOUT THIS TOOL
A6: Purpose: | B6: This Excel-based tool operationalizes the Solidarity Profiling Framework, translating pluriversal solidarity principles into a multidimensional profiling methodology for global health decision-making.
B7: Rather than generating a universal index or ranking, the framework captures diverse expressions of solidaristic practice across institutional and sociopolitical contexts.
A9: Target Users: | B9: • Funders and donors evaluating programs for solidarity alignment
B10: • Program analysts and managers conducting self-assessments
B11: • Government entities assessing partner programs
B12: • Researchers studying global health equity and solidarity
B13: • Civil society organizations monitoring health initiatives
A15: RATIONALE
A17: Why This Tool?: | B17: Traditional evaluations measure technical outcomes (efficiency, effectiveness, financial protection) but rarely examine the relational, ethical, and governance processes through which outcomes are pursued.
B18: 1. Generates solidarity PROFILES, not composite indices or rankings
B19: 2. Preserves conceptual plurality and contextual interpretation
B20: 3. Treats indicators as context-sensitive analytical prompts, not fixed metrics
B21: 4. Embeds reflexivity, transparency, and shared interpretation in assessment
B22: 5. Incorporates anti-capture safeguards and human rights floors
B23: 6. Detects 'solidarity washing' - rhetorical solidarity without substance
A24: THEORETICAL FRAMEWORK
A26: Three Dimensions: | B26: The tool organizes assessment around three core questions:
A28: Dimension | B28: Question | C28: Domains | D28: Focus
A29: WHAT (Orientation) | B29: What values guide the program? | C29: D1-D3 | D29: Equity, common good, mutual responsibility
A30: HOW (Process) | B30: How is the program implemented? | C30: D4-D6 | D30: Power, participation, transparency
A31: TO WHAT END (Outcomes) | B31: What outcomes does it seek? | C31: D7-D9 | D31: Sustainability, trust, transformation
A33: Nine Domains:
A34: Domain | B34: Description | C34: Key Question
A35: D1: Equity & Justice | B35: Prioritization of marginalized populations | C35: Who benefits? Are resources distributed by need?
A36: D2: Common Good | B36: Focus on collective health outcomes | C36: Are public goods shared openly?
A37: D3: Mutual Responsibility | B37: Shared accountabilities between parties | C37: Who bears risk? Is there reciprocity?
A38: D4: Power Transformation | B38: Redistribution of decision-making authority | C38: Who decides? Who controls resources?
A39: D5: Inclusive Participation | B39: Meaningful community involvement | C39: Are communities co-deciding or just consulted?
A40: D6: Transparency | B40: Open information and accountability | C40: Can communities hold actors accountable?
A41: D7: Sustainability | B41: Building lasting local capacity | C41: Will impact continue? Is ownership growing?
A42: D8: Relational Trust | B42: Quality of relationships and respect | C42: Is there mutual respect? Commitments honored?
A43: D9: Transformative Impact | B43: Dismantling inequitable structures | C43: Does it challenge root causes?
A45: METHODOLOGY
A47: Approach: | B47: MIXED-METHODS combining quantitative ratings and qualitative evidence
B48: • Semi-quantitative ratings (1-5 scale) for structured comparison
B49: • Qualitative indicator prompts to preserve nuance
B50: • Evidence documentation to ground assessments in reality
B51: • Confidence levels to signal uncertainty
B52: • Integrity checks to detect contradictions and risks
A54: Rating Scale:
A55: Rating | B55: Level | C55: Description
A56: 1 | B56: Emerging/Minimal | C56: Little evidence of solidarity dimension
A57: 2 | B57: Partial/Inconsistent | C57: Some elements but notable gaps
A58: 3 | B58: Moderate/Developing | C58: Clear effort but not yet embedded
A59: 4 | B59: Strong/Consistent | C59: Robust expression embedded in practice
A60: 5 | B60: Transformative/Exemplary | C60: Exceptional, advances solidarity beyond scope
A62: SHEET DESCRIPTIONS
A64: Sheet | B64: Purpose | C64: Contents
A65: Dashboard | B65: Summary view of results | C65: Metrics, visual ratings, risk flags, narrative
A66: Input_Context | B66: Capture program metadata | C66: Program ID, actors, characteristics
A67: Input_Domains | B67: Core solidarity assessment | C67: 9 domains with ratings, prompts, evidence
A68: Input_Integrity | B68: Risk assessment | C68: Alignment checks, voice analysis, risks
A69: Reference | B69: Framework guide | C69: Definitions, scales, interpretation
A70: Calculation | B70: Backend processing | C70: Formulas (do not modify)
A71: Readme | B71: Documentation | C71: This sheet - overview and rationale
A72: HowTo | B72: User guide | C72: Step-by-step instructions
A74: FILLED SAMPLE SHEETS (HIV Programming in Nigeria):
A75: • Input_Context - Contains sample program details for PEPFAR Nigeria
A76: • Input_Domains - Contains sample ratings and evidence for all 9 domains
A77: • Input_Integrity - Contains sample risk assessment and solidarity type
A78: • Dashboard - Auto-populates from sample data with formulas
A80: BLANK TEMPLATE SHEETS (For New Assessments):
A81: • Blank_Context - Empty template for program identification
A82: • Blank_Domains - Empty template with indicator prompts for each domain
A83: • Blank_Integrity - Empty template for integrity checks and risk assessment
A85: HOW TO USE FOR A NEW ASSESSMENT:
A86: 1. Copy the Blank_* sheets to create your own assessment
A87: 2. Or clear data from Input_* sheets (keeping formulas in Dashboard)
... A99: The tool cannot capture all dimensions - local knowledge remains essential.

Sheet HowTo
A1: HOW TO USE THE SOLIDARITY PROFILE ASSESSMENT TOOL
A2: Step-by-Step User Guide
A4: OVERVIEW OF THE ASSESSMENT PROCESS
A6: Step | B6: Action | C6: Sheet | D6: Focused Time Estimate
A7: 1 | B7: Gather background documents and evidence | C7: N/A (Preparation) | D7: 1-2 hours
A8: 2 | B8: Complete program context information | C8: Input_Context | D8: 15-30 minutes
A9: 3 | B9: Assess all 9 solidarity domains | C9: Input_Domains | D9: 2-4 hours
A10: 4 | B10: Complete integrity and risk checks | C10: Input_Integrity | D10: 30-60 minutes
A11: 5 | B11: Review auto-generated results | C11: Dashboard | D11: 15-30 minutes
A12: 6 | B12: Interpret and document findings | C12: Dashboard + Reference | D12: 30-60 minutes
A14: STEP 0: PREPARATION - BEFORE YOU BEGIN
A16: Gather These Materials:
A17: Document Type | B17: Why It's Needed | C17: Where to Find It
A18: Program proposal/design documents | B18: Understanding stated goals and approach | C18: Funder/implementing organization files
A19: Budget and financial reports | B19: Analyzing resource allocation and cost distribution | C19: Finance department, grant reports
A20: Monitoring & evaluation reports | B20: Evidence of outcomes and implementation | C20: M&E team, program reports
A21: Meeting minutes/governance records | B21: Understanding decision-making processes | C21: Program management, steering committees
A22: Community feedback/consultation records | B22: Evidence of participation and voice | C22: Community liaison, field reports
A23: Partnership agreements/MOUs | B23: Understanding roles and responsibilities | C23: Legal/contracts, partner organizations
A24: Previous evaluations or reviews | B24: Historical context and identified issues | C24: Evaluation archives, donor reports
A26: Key Informants to Consult:
A27: • Program managers and coordinators
A28: • Community representatives and beneficiaries
A29: • Local implementing partners
A30: • Government counterparts (if applicable)
A31: • Funder representatives
A33: SHEET 1: INPUT_CONTEXT - Program Metadata
A35: Purpose:- not more than 300 words | B35: Establishes the context for interpretation. Without this, results cannot be properly understood or compared.
A37: Field | B37: Why It Matters | C37: How to Complete | D37: Data Source
A38: Program Name | B38: Identification and tracking | C38: Enter official program name | D38: Program documents
A39: Organisation/Funder | B39: Understanding power dynamics | C39: Primary funding/implementing org | D39: Grant agreements
A40: Country/Region | B40: Contextual interpretation | C40: Geographic scope of activities | D40: Program documents
A41: Sector | B41: Sector-specific considerations | C41: e.g., Vaccine delivery, PHC, Research | D41: Program description
A42: Start/End Dates | B42: Program maturity assessment | C42: Format: MM/YYYY or 'Ongoing' | D42: Grant agreements
A43: Assessment Date | B43: Tracking when assessment done | C43: Date of this assessment | D43: Current date
A44: Assessor Name/Role | B44: Accountability and perspective | C44: Your name and position | D44: Self-reported
A46: Actor Mapping (CRITICAL): | B46: This section reveals power dynamics - who has authority, resources, and voice.
A47: Primary Funders | B47: Follow the money to understand influence | C47: List ALL major funding sources | D47: Financial reports
A48: Implementing Partners | B48: Who does the work on ground? | C48: Local and international orgs | D48: Partnership agreements
A49: Community Actors | B49: Who represents affected populations? | C49: Community groups, local leaders | D49: Stakeholder mapping
A50: Government Involvement | B50: State role and engagement | C50: Select level and describe role | D50: MOUs, govt correspondence
A52: Program Characteristics: | B52: Determines appropriate comparison frame and expectations.
A53: Program Type | B53: Emergency vs long-term have different solidarity expressions | C53: Select from dropdown | D53: Program design docs
A54: Funding Model | B54: Grant vs partnership affects power dynamics | C54: Select from dropdown | D54: Agreements
A55: Scale | B55: Local programs differ from global initiatives | C55: Select from dropdown | D55: Program scope docs
A56: Budget Range | B56: Resource level affects what's possible | C56: Select range from dropdown | D56: Budget documents
A58: SHEET 2: INPUT_DOMAINS - Core Solidarity Assessment
A60: Purpose: | B60: This is the HEART of the assessment. Rate each of 9 domains with evidence-based justification.
A62: For EACH Domain, Complete:
A63: Component | B63: What to Enter | C63: Why It Matters | D63: Tips
A64: RATING (1-5) | B64: Select rating from dropdown | C64: Enables structured comparison | D64: Be honest - 3 is acceptable!
A65: Indicator Prompts | B65: Answer each guiding question | C65: Forces systematic thinking | D65: Use evidence, not assumptions
A66: Evidence Type | B66: Select type: Documents/Interviews/Observations/Multiple | C66: Grounds assessment in reality | D66: Multiple sources = stronger
A67: Evidence Summary | B67: Describe the evidence supporting your rating | C67: Audit trail for credibility | D67: Be specific - cite sources
A68: Confidence Level | B68: Select: Low/Medium/High | C68: Signals assessment reliability | D68: Low confidence is valuable data
A70: Rating Guidance:
A71: Rating | B71: When to Use | C71: Evidence Needed
A72: 1 - Emerging | B72: Little/no evidence; possibly contrary to solidarity | C72: Absence of evidence or contrary evidence
A73: 2 - Partial | B73: Some elements but inconsistent; notable gaps | C73: Mixed or incomplete evidence
A74: 3 - Moderate | B74: Clear effort; developing but not embedded | C74: Evidence of intention and some action
A75: 4 - Strong | B75: Robust expression; embedded in practice | C75: Consistent evidence across multiple sources
A76: 5 - Transformative | B76: Exceptional; advances solidarity beyond program | C76: Strong evidence of systemic impact
A78: Domain-Specific Guidance:
A79: Domain | B79: Key Evidence to Look For | C79: Red Flags
A80: D1: Equity & Justice | B80: Targeting criteria, resource allocation data, disaggregated outcomes | C80: Elite capture, political allocation, neglected populations
A81: D2: Common Good | B81: Public vs private benefit balance, knowledge sharing, system strengthening | C81: Private gain prioritized, parallel systems created
A82: D3: Mutual Responsibility | B82: Risk-sharing arrangements, accountability mechanisms, reciprocity | C82: One-way dependency, all risk on local actors
A83: D4: Power Transformation | B83: Decision-making records, budget control, authority transitions | C83: All decisions made externally, no local control
A84: D5: Inclusive Participation | B84: Consultation records, community governance roles, accessibility | C84: Token consultation, excluded groups, inaccessible processes
A85: D6: Transparency | B85: Information accessibility, accountability mechanisms, honest reporting | C85: Hidden information, no feedback loops, only success stories
A86: D7: Sustainability | B86: Capacity building plans, transition strategies, local ownership growth | C86: No exit plan, dependency creation, parallel structures
A87: D8: Relational Trust | B87: Relationship quality indicators, conflict resolution, commitment follow-through | C87: Broken promises, disrespectful interactions, mistrust
A88: D9: Transformative Impact | B88: System change evidence, root cause addressing, structural shifts | C88: Treating symptoms only, maintaining status quo
A90: SHEET 3: INPUT_INTEGRITY - Risk & Contradiction Assessment | C90: SHEET 3: INPUT_INTEGRITY - Risk & Contradiction Assessment
A92: Purpose: | B92: Detects hidden dynamics that domain scores might miss - especially 'solidarity washing' and power imbalances.
A94: Section | B94: What to Assess | C94: Why It Matters | D94: How to Investigate
A95: 1. Alignment Check | B95: Contradictions between goals and other org activities | C95: Reveals organizational hypocrisy | D95: Review funder's full portfolio
A96: 2. Cost Distribution | B96: Who bears implementation burdens | C96: Hidden extraction and cost-shifting | D96: Analyze indirect cost coverage
A97: 3. Voice & Decision Reality | B97: Actual vs stated community involvement | C97: Distinguishes real from token participation | D97: Interview community actors
A98: 4. Solidarity Type | B98: Classify the overall solidarity expression | C98: Provides summary characterization | D98: Synthesize all evidence
A99: 5. Risk Assessment | B99: Rate risks in 4 key areas | C99: Flags concerns for attention | D99: Based on all prior sections
A101: Solidarity Types Explained:
A102: Type | B102: Description | C102: Indicators
A103: Symbolic/Rhetorical | B103: Solidarity language without substantive action | C103: Nice words, no resource shift, power unchanged
A104: Partial/Instrumental | B104: Solidarity as means to other ends | C104: Some action but serving funder interests primarily
A105: Substantive/Relational | B105: Genuine mutual commitment and partnership | C105: Real power sharing, mutual accountability, trust
A106: Transformative | B106: Active dismantling of inequitable structures | C106: System change, challenging root causes, decolonizing
A108: Risk Level Guidance:
A109: Risk Area | B109: Low | C109: Medium | D109: High
A110: Solidarity Washing | B110: Actions match rhetoric | C110: Some gaps between words/actions | D110: Major contradictions evident
A111: Power Imbalance | B111: Genuine power sharing | C111: Some local authority but limited | D111: External actors dominate
A112: Sustainability | B112: Strong local ownership growing | C112: Some capacity but dependent | D112: No transition plan, dependency
A113: Inclusion Gap | B113: Marginalized groups centered | C113: Included but not leading | D113: Key groups excluded
A115: SHEET 4: DASHBOARD - Interpreting Results
A117: Purpose: | B117: Auto-generated summary of your assessment. Use for reporting and decision-making.
A119: Dashboard Section | B119: What It Shows | C119: How to Interpret
A120: Program Summary | B120: Basic program info pulled from Input_Context | C120: Verify accuracy
A121: Domain Ratings | B121: All 9 domain ratings with levels | C121: Look for patterns - are some dimensions weaker?
A122: Dimension Profile | B122: WHAT/HOW/END averages | C122: Identifies which dimension needs most attention
A123: Risk Flags | B123: Color-coded risk alerts | C123: Red = urgent attention; Green = lower concern
...

Sheet Dashboard
A1: SOLIDARITY PROFILE ASSESSMENT DASHBOARD
A2: SAMPLE ASSESSMENT: PEPFAR Nigeria HIV Treatment & Prevention Program
A3: PROGRAM SUMMARY | G3: DOMAIN RATINGS
A4: Assesment Title | B4: =Calculations!B51 -> PEPFAR Nigeria | C4: Organisation: | E4: KEY FINDINGS - PEPFAR NIGERIA | I4: Level
A5: Assessor: | B5: Paul Ongboche | C5: Sector: | E5: STRENGTHS: | F5: • Strong equity focus on high-burden states and vulnerable populations | G5: D1 | H5: =C18 -> 3 | I5: =IF(H5>=4,"Strong",IF(H5>=3,"Moderate",IF(H5>=2,"Partial","Emerging"))) -> Moderate
A6: Date: | B6: 46190 | C6: Scale: | F6: • Robust M&E systems and shared accountability mechanisms | G6: D2 | H6: =C19 -> 4 | I6: =IF(H6>=4,"Strong",IF(H6>=3,"Moderate",IF(H6>=2,"Partial","Emerging"))) -> Strong
A7: Program: | B7: PEPFAR Nigeria HIV Treatment & Prevention | C7: Assessor: | F7: • Significant systems strengthening (CHIPS, laboratory networks) | G7: D3 | H7: =C20 -> 2 | I7: =IF(H7>=4,"Strong",IF(H7>=3,"Moderate",IF(H7>=2,"Partial","Emerging"))) -> Partial
A8: Country: | B8: Nigeria (Multi-State) | F8: • 95% viral suppression among adults on treatment | G8: D4 | H8: =C21 -> 2 | I8: =IF(H8>=4,"Strong",IF(H8>=3,"Moderate",IF(H8>=2,"Partial","Emerging"))) -> Partial
A9: Period: | B9: 2021-2025 | C9: Overall Confidence: | E9: GAPS: | F9: • Heavy donor dependency (81% external funding) | G9: D5 | H9: =C22 -> 1 | I9: =IF(H9>=4,"Strong",IF(H9>=3,"Moderate",IF(H9>=2,"Partial","Emerging"))) -> Emerging
A10: Assessment Status: | B10: =IF(Calculations!B27=9,"Complete",IF(Calculations!B27>0,"Partial","Not Started")) -> Complete | F10: • Limited power transformation - priorities set by funders | G10: D6 | H10: =C23 -> 2 | I10: =IF(H10>=4,"Strong",IF(H10>=3,"Moderate",IF(H10>=2,"Partial","Emerging"))) -> Partial
A11: DIMENSION PROFILE | F11: • Sustainability risks exposed by 2025 USAID funding freeze | G11: D7 | H11: =C24 -> 2 | I11: =IF(H11>=4,"Strong",IF(H11>=3,"Moderate",IF(H11>=2,"Partial","Emerging"))) -> Partial
A12: Dimension | B12: Avg Rating | C12: Level | D12: TENSIONS: | F12: • Legal barriers to inclusive KP programming | G12: D8 | H12: =C25 -> 2 | I12: =IF(H12>=4,"Strong",IF(H12>=3,"Moderate",IF(H12>=2,"Partial","Emerging"))) -> Partial
A13: WHAT (Orientation) | B13: =Calculations!B19 -> 1 | C13: =Calculations!C19 -> Emerging | D13: =IF(Calculations!D19>=2.5,"High",IF(Calculations!D19>=1.5,"Medium","Low")) -> Medium | F13: • Health outcomes strong BUT local ownership weak | G13: D9 | H13: =C26 -> 4 | I13: =IF(H13>=4,"Strong",IF(H13>=3,"Moderate",IF(H13>=2,"Partial","Emerging"))) -> Strong
A14: HOW (Process) | B14: =Calculations!B20 -> 1.6666667 | C14: =Calculations!C20 -> Emerging | D14: =IF(Calculations!D20>=2.5,"High",IF(Calculations!D20>=1.5,"Medium","Low")) -> High | F14: • Equity in targeting BUT exclusion of KP due to legal environment | G14: KEY INSIGHTS
A15: TO WHAT END (Outcomes) | B15: =Calculations!B21 -> 2.6666667 | C15: =Calculations!C21 -> Partial | D15: =IF(Calculations!D21>=2.5,"High",IF(Calculations!D21>=1.5,"Medium","Low")) -> Medium | F15: • Technical solidarity strong BUT structural solidarity limited | G15: Insight Type | H15: Domain | I15: Finding
A16: SOLIDARITY PROFILE SUMMARY | G16: Strongest Area | H16: =INDEX(Calculations!A6:A14,MATCH(MAX(Calculations!D6:D14),Calculations!D6:D14,0)) -> D9: Transformative Impact | I16: =CONCATENATE("Rating: ",MAX(Calculations!D6:D14)) -> Rating: 4
A17: Dimension | E17: Visual | G17: Area for Growth | H17: =INDEX(Calculations!A6:A14,MATCH(MIN(Calculations!D6:D14),Calculations!D6:D14,0)) -> D2: Common Good Orientation | I17: =CONCATENATE("Rating: ",MIN(Calculations!D6:D14)) -> Rating: 0
A18: WHAT | B18: D1: Equity & Justice | C18: =Input_Domains!B6 -> 3 | D18: =IF(C18>=4,"Strong",IF(C18>=3,"Moderate",IF(C18>=2,"Partial","Emerging"))) -> Moderate | E18: =REPT("●",C18)&REPT("○",5-C18) -> ●●●○○ | G18: Rating Gap | H18: =MAX(Calculations!D6:D14)-MIN(Calculations!D6:D14) -> 4 | I18: =IF(H18>2,"Large variation across domains",IF(H18>1,"Moderate variation","Consistent ratings")) -> Large variation across domains
A19: WHAT | B19: D2: Common Good | C19: =Input_Domains!B22 -> 4 | D19: =IF(C19>=4,"Strong",IF(C19>=3,"Moderate",IF(C19>=2,"Partial","Emerging"))) -> Strong | E19: =REPT("●",C19)&REPT("○",5-C19) -> ●●●●○ | G19: NARRATIVE SUMMARY
A20: WHAT | B20: D3: Mutual Responsibility | C20: =Input_Domains!B38 -> 2 | D20: =IF(C20>=4,"Strong",IF(C20>=3,"Moderate",IF(C20>=2,"Partial","Emerging"))) -> Partial | E20: =REPT("●",C20)&REPT("○",5-C20) -> ●●○○○ | G20: =IF(Calculations!B27=0,"Assessment not yet started. Please complete the input sheets.",CONCATENATE("This ",Calculations!B55," program in ",Calculations!B53," demonstrates ",Calculations!C19," orientation (WHAT), ",Calculations!C20," process (HOW), and ",Calculations!C21," outcomes focus (TO WHAT END).")) -> This 0 program in Nigeria demonstrates Emerging orientation (WHAT), Emerging process (HOW), and Partial outcomes focus (TO WHAT END).
A21: HOW | B21: D4: Power Transformation | C21: =Input_Domains!B54 -> 2 | D21: =IF(C21>=4,"Strong",IF(C21>=3,"Moderate",IF(C21>=2,"Partial","Emerging"))) -> Partial | E21: =REPT("●",C21)&REPT("○",5-C21) -> ●●○○○ | G21: =IF(Calculations!B27=0,"",CONCATENATE("Strongest in: ",INDEX(Calculations!A6:A14,MATCH(MAX(Calculations!D6:D14),Calculations!D6:D14,0)),". Area for development: ",INDEX(Calculations!A6:A14,MATCH(MIN(Calculations!D6:D14),Calculations!D6:D14,0)),".")) -> Strongest in: D9: Transformative Impact. Area for development: D2: Common Good Orientation.
A22: HOW | B22: D5: Inclusive Participation | C22: =Input_Domains!B72 -> 1 | D22: =IF(C22>=4,"Strong",IF(C22>=3,"Moderate",IF(C22>=2,"Partial","Emerging"))) -> Emerging | E22: =REPT("●",C22)&REPT("○",5-C22) -> ●○○○○ | G22: VISUAL RATING BARS
A23: HOW | B23: D6: Transparency | C23: =Input_Domains!B88 -> 2 | D23: =IF(C23>=4,"Strong",IF(C23>=3,"Moderate",IF(C23>=2,"Partial","Emerging"))) -> Partial | E23: =REPT("●",C23)&REPT("○",5-C23) -> ●●○○○ | G23: Domain | H23: Rating (1-5) | I23: Visual
A24: TO WHAT END | B24: D7: Sustainability | C24: =Input_Domains!B104 -> 2 | D24: =IF(C24>=4,"Strong",IF(C24>=3,"Moderate",IF(C24>=2,"Partial","Emerging"))) -> Partial | E24: =REPT("●",C24)&REPT("○",5-C24) -> ●●○○○ | G24: =B18 -> D1: Equity & Justice | H24: =H5 -> 3 | I24: =REPT("█",IF(ISNUMBER(H24),H24,0))&REPT("░",5-IF(ISNUMBER(H24),H24,0)) -> ███░░
A25: TO WHAT END | B25: D8: Relational Trust | C25: =Input_Domains!B120 -> 2 | D25: =IF(C25>=4,"Strong",IF(C25>=3,"Moderate",IF(C25>=2,"Partial","Emerging"))) -> Partial | E25: =REPT("●",C25)&REPT("○",5-C25) -> ●●○○○ | G25: =B19 -> D2: Common Good | H25: =H6 -> 4 | I25: =REPT("█",IF(ISNUMBER(H25),H25,0))&REPT("░",5-IF(ISNUMBER(H25),H25,0)) -> ████░
A26: TO WHAT END | B26: D9: Transformative Impact | C26: =Input_Domains!B136 -> 4 | D26: =IF(C26>=4,"Strong",IF(C26>=3,"Moderate",IF(C26>=2,"Partial","Emerging"))) -> Strong | E26: =REPT("●",C26)&REPT("○",5-C26) -> ●●●●○ | G26: =B20 -> D3: Mutual Responsibility | H26: =H7 -> 2 | I26: =REPT("█",IF(ISNUMBER(H26),H26,0))&REPT("░",5-IF(ISNUMBER(H26),H26,0)) -> ██░░░
A27: Partial / Instrumental | B27: =IF(Calculations!B44<>"","✓ Selected","") -> ✓ Selected | G27: =B21 -> D4: Power Transformation | H27: =H8 -> 2 | I27: =REPT("█",IF(ISNUMBER(H27),H27,0))&REPT("░",5-IF(ISNUMBER(H27),H27,0)) -> ██░░░
G28: =B22 -> D5: Inclusive Participation | H28: =H9 -> 1 | I28: =REPT("█",IF(ISNUMBER(H28),H28,0))&REPT("░",5-IF(ISNUMBER(H28),H28,0)) -> █░░░░
A29: DIMENSION AVERAGES | G29: =B23 -> D6: Transparency | H29: =H10 -> 2 | I29: =REPT("█",IF(ISNUMBER(H29),H29,0))&REPT("░",5-IF(ISNUMBER(H29),H29,0)) -> ██░░░
A30: WHAT (Equity, Inclusivity, Justice) | B30: =AVERAGE(C18:C20) -> 3 | C30: =IF(B30>=4,"Strong",IF(B30>=3,"Moderate",IF(B30>=2,"Partial","Emerging"))) -> Moderate | D30: =REPT("█",ROUND(B30,0))&REPT("░",5-ROUND(B30,0)) -> ███░░ | G30: =B24 -> D7: Sustainability | H30: =H11 -> 2 | I30: =REPT("█",IF(ISNUMBER(H30),H30,0))&REPT("░",5-IF(ISNUMBER(H30),H30,0)) -> ██░░░
A31: HOW (Reciprocity, Accountability, Power) | B31: =AVERAGE(C21:C23) -> 1.6666667 | C31: =IF(B31>=4,"Strong",IF(B31>=3,"Moderate",IF(B31>=2,"Partial","Emerging"))) -> Emerging | D31: =REPT("█",ROUND(B31,0))&REPT("░",5-ROUND(B31,0)) -> ██░░░ | G31: =B25 -> D8: Relational Trust | H31: =H12 -> 2 | I31: =REPT("█",IF(ISNUMBER(H31),H31,0))&REPT("░",5-IF(ISNUMBER(H31),H31,0)) -> ██░░░
A32: TO WHAT END (Sustainability, Systems, Outcomes) | B32: =AVERAGE(C24:C26) -> 2.6666667 | D32: =REPT("█",ROUND(B32,0))&REPT("░",5-ROUND(B32,0)) -> ███░░ | G32: =B26 -> D9: Transformative Impact | H32: =H13 -> 4 | I32: =REPT("█",IF(ISNUMBER(H32),H32,0))&REPT("░",5-IF(ISNUMBER(H32),H32,0)) -> ████░
A33: OVERALL SOLIDARITY PROFILE | B33: =AVERAGE(B30:B32) -> 2.4444444 | C33: =IF(B33>=4,"Strong",IF(B33>=3,"Moderate",IF(B33>=2,"Partial","Emerging"))) -> Partial
A34: Solidaristic Funding Fit? | B34: =IF(Calculations!B26>=3.5,"Strong fit for solidaristic funding",IF(Calculations!B26>=2.5,"Moderate fit - some areas need strengthening",IF(Calculations!B26>=1.5,"Weak fit - significant redesign needed","Not suitable for solidaristic funding"))) -> Weak fit - significant redesign needed
A35: RISK FLAGS & ALERTS
A36: Solidarity Washing Risk | B36: =Input_Integrity!B33 -> High | C36: =IF(B36="High","⚠️ HIGH RISK",IF(B36="Med","⚡ MODERATE","✓ LOW")) -> ⚠️ HIGH RISK
A37: Power Imbalance Risk | B37: =Input_Integrity!B34 -> High | C37: =IF(B37="High","⚠️ HIGH RISK",IF(B37="Med","⚡ MODERATE","✓ LOW")) -> ⚠️ HIGH RISK
A38: Sustainability Risk | B38: =Input_Integrity!B35 -> Med | C38: =IF(B38="High","⚠️ HIGH RISK",IF(B38="Med","⚡ MODERATE","✓ LOW")) -> ⚡ MODERATE
A39: Inclusion Gap Risk | B39: =Input_Integrity!B36 -> Med | C39: =IF(B39="High","⚠️ HIGH RISK",IF(B39="Med","⚡ MODERATE","✓ LOW")) -> ⚡ MODERATE
A40: Solidarity Type Observed: | B40: =Input_Integrity!B14 -> No
A41: AUTO-GENERATED NARRATIVE SUMMARY
A42: ="This program demonstrates "&C33&" overall solidarity ("&TEXT(B33,"0.0")&"/5). "&IF(B30>B31,"The program is stronger in WHAT it addresses than HOW it operates. ",IF(B31>B30,"The program shows stronger process-based solidarity (HOW) than outcome focus (WHAT). ",""))&IF(C23="Partial","Power transformation remains limited - local actors have constrained decision-making authority. ","")&IF(C24="Partial","Sustainability is a concern with heavy reliance on external funding. ","")&"Solidarity type observed: "&B40&". "&IF(B37="High","⚠️ CRITICAL: High dependency risk detected.","") -> This program demonstrates Partial overall solidarity (2.4/5). The program is stronger in WHAT it addresses than HOW it operates. Solidarity type observed: No. ⚠️ CRITICAL: High dependency risk detected.
A47: DECISION SUPPORT & RECOMMENDATIONS
A48: Strongest Domain: | B48: {=INDEX({"D1: Equity","D2: Inclusivity","D3: Justice","D4: Reciprocity","D5: Accountability","D6: Power","D7: Sustainability","D8: Systems","D9: Outcomes"},MATCH(MAX(C18:C26),C18:C26,0))} -> D2: Inclusivity | C48: ="(Score: "&MAX(C18:C26)&")" -> (Score: 4)
A49: Weakest Domain: | B49: {=INDEX({"D1: Equity","D2: Inclusivity","D3: Justice","D4: Reciprocity","D5: Accountability","D6: Power","D7: Sustainability","D8: Systems","D9: Outcomes"},MATCH(MIN(C18:C26),C18:C26,0))} -> D5: Accountability | C49: ="(Score: "&MIN(C18:C26)&")" -> (Score: 1)
A51: PRIORITY ACTIONS FOR PEPFAR NIGERIA:
A52: 1 | B52: Accelerate domestic financing transition - increase government allocation beyond current $3.2M commitment
A53: 2 | B53: Strengthen power transformation - involve local actors in COP priority-setting, not just implementation
A54: 3 | B54: Address legal barriers to KP inclusion - advocate for policy reforms enabling full participation
A55: 4 | B55: Diversify funding sources - engage private sector, explore South-South partnerships
A56: 5 | B56: Complete domestic ARV production capacity by end 2025 as planned
A58: FIT FOR SOLIDARISTIC FUNDING: | B58: =IF(B33>=4,"✓ YES - Strong solidarity profile",IF(B33>=3,"⚡ CONDITIONAL - Moderate solidarity with improvement areas",IF(B33>=2,"⚠️ CONCERNS - Significant gaps in solidarity dimensions","✗ NO - Fundamental solidarity deficits"))) -> ⚠️ CONCERNS - Significant gaps in solidarity dimensions

Sheet Input_Context
A1: SOLIDARITY PROFILE ASSESSMENT TOOL
A2: Section 1: Program Context & Metadata
A4: PROGRAM IDENTIFICATION
A5: Field | C5: Guidance
A6: Program Name | B6: PEPFAR Nigeria | C6: Enter the official name of the health program
A7: Organisation / Funder | B7: USG | C7: Primary organisation or funding entity
A8: Country / Region | B8: Nigeria | C8: Geographic scope of the program
A9: Sector | B9: Health - HIV Program | C9: e.g., Vaccine delivery, Primary healthcare, Research, Maternal health
A10: Program Start Date | C10: Format: MM/YYYY
A11: Program End Date | C11: Format: MM/YYYY (or 'Ongoing')
A12: Assessment Date | C12: Date this assessment is being completed
A13: Assessor Name | C13: Name of person completing this assessment
A14: Assessor Role | C14: e.g., Funder, Program Manager, Researcher, Government Official
A16: ACTOR MAPPING (Critical for Power Analysis)
A17: Field | C17: Guidance
A18: Primary Funder(s) | C18: List all major funding sources
A19: Implementing Partners | C19: Local and international implementing organisations
A20: Community Actors Involved | C20: Community groups, local leaders, beneficiary representatives
A21: Government Involvement | C21: Select: Yes - National / Yes - Subnational / No / Limited
A22: Government Role Description | C22: Describe the nature of government engagement
A24: PROGRAM CHARACTERISTICS
A25: Field | B25: Input | C25: Options
A26: Program Type | C26: Emergency Response / Long-term System Strengthening / Both
A27: Funding Model | C27: Grant / Partnership / Contractual / Mixed
A28: Program Scale | C28: Local / National / Regional / Global
A29: Budget Range (USD) | C29: < 100K / 100K-1M / 1M-10M / 10M-100M / > 100M
A30: Target Population Size | C30: Approximate number of direct beneficiaries

Sheet Input_Domains
A1: SOLIDARITY PROFILE ASSESSMENT - DOMAIN-BASED ASSESSMENT
A2: Instructions: For each domain, provide a rating (1-5), respond to indicator prompts, document evidence, and indicate confidence level.
A3: RATING SCALE: 1=Emerging/Minimal | 2=Partial/Inconsistent | 3=Moderate/Developing | 4=Strong/Consistent | 5=Transformative/Exemplary
A5: D1: EQUITY & JUSTICE | G5: Dimension: WHAT (Orientation)
A6: RATING (1-5): | B6: 3
A7: INDICATOR PROMPTS
A8: 1. To what extent does the program prioritize the needs of marginalized or underserved populations?
A9: Response:
A10: 2. Are resources distributed based on need rather than political or economic factors?
A11: Response:
A12: 3. Does the program address root causes of health inequities, not just symptoms?
A13: Response:
A14: EVIDENCE
A15: Evidence Type: | B15: Interviews
A16: Evidence Summary:
A18: CONFIDENCE LEVEL: | B18: Medium
A21: D2: COMMON GOOD ORIENTATION | G21: Dimension: WHAT (Orientation)
A22: RATING (1-5): | B22: 4
A23: INDICATOR PROMPTS
A24: 1. Does the program prioritize collective health outcomes over individual or organizational gains? | B24: Program prioritizes collective health outcomes through public health approach. Some organizational interests in maintaining program presence.
A25: Response:
A26: 2. Are public goods (knowledge, technologies) shared openly rather than restricted? | B26: Knowledge shared through open data platforms (DATIM). Some technologies proprietary but most accessible.
A27: Response:
A28: 3. Is the program designed to strengthen public health systems rather than parallel structures? | B28: Program strengthens public systems (CHIPS, laboratory networks) rather than creating parallel structures.
A29: Response:
A30: EVIDENCE
A31: Evidence Type: | B31: Observations
A32: Evidence Summary:
A34: CONFIDENCE LEVEL: | B34: High
A37: D3: MUTUAL RESPONSIBILITY | G37: Dimension: WHAT (Orientation)
A38: RATING (1-5): | B38: 2
A39: INDICATOR PROMPTS
A40: 1. Are responsibilities and accountabilities clearly shared between all parties? | B40: Responsibilities shared through COP process and Joint Annual Reviews. Government has formal role but limited fiscal contribution.
A41: Response:
A42: 2. Do all actors (funders, implementers, communities) bear appropriate shares of risk? | B42: Risk primarily borne by communities when funding disrupted. Funders retain most control over risk allocation.
A43: Response:
A44: 3. Is there evidence of reciprocal obligations rather than one-way dependency? | B44: Some reciprocal obligations exist but dependency remains. Government committed $3.2M for transition.
A45: Response:
A46: EVIDENCE
A47: Evidence Type:
A48: Evidence Summary:
A50: CONFIDENCE LEVEL:
A53: D4: POWER TRANSFORMATION | G53: Dimension: HOW (Process)
A54: RATING (1-5): | B54: 2
A55: INDICATOR PROMPTS
A56: 1. To what extent are decision-making powers shared with local actors?
A57: Response:
A58: 2. Who sets priorities and controls funding allocation?
A59: Response:
A60: 3. Are there mechanisms to shift authority over time to local ownership?
A61: Response:
A62: 4. Is there evidence of addressing historical power imbalances?
A63: Response:
A64: EVIDENCE
A65: Evidence Type:
A66: Evidence Summary:
B67: COP planning documents, Partner agreements, NACA transition strategy, March 2026 Nairobi workshop proceedings
A68: CONFIDENCE LEVEL:
B69: High
A71: D5: INCLUSIVE PARTICIPATION | G71: Dimension: HOW (Process)
A72: RATING (1-5): | B72: 1
A73: INDICATOR PROMPTS
A74: 1. Are affected communities meaningfully involved in program design?
A75: Response:
A76: 2. Do marginalized groups have genuine voice in decision-making (not just consultation)?
A77: Response:
A78: 3. Are participation mechanisms accessible and culturally appropriate?
A79: Response:
A80: EVIDENCE
A81: Evidence Type:
A82: Evidence Summary:
B83: NEPWHAN meeting minutes, CCM records, Community consultation reports
A84: CONFIDENCE LEVEL:
B85: Medium
A87: D6: TRANSPARENCY & ACCOUNTABILITY | G87: Dimension: HOW (Process)
A88: RATING (1-5): | B88: 2
A89: INDICATOR PROMPTS
A90: 1. Is information about funding, decisions, and outcomes openly accessible?
A91: Response:
A92: 2. Are there mechanisms for communities to hold implementing actors accountable?
A93: Response:
A94: 3. Is there honest reporting of failures and challenges, not just successes?
A95: Response:
A96: EVIDENCE
A97: Evidence Type:
A98: Evidence Summary:
B99: NACA coordination reports, CCM meeting records, M&E framework documents
A100: CONFIDENCE LEVEL:
B101: High
A103: D7: SUSTAINABILITY & SOVEREIGNTY | G103: Dimension: TO WHAT END (Outcomes)
A104: RATING (1-5): | B104: 2
A105: INDICATOR PROMPTS
A106: 1. Does the program strengthen local health system capacity for long-term sustainability?
A107: Response:
A108: 2. Is there a clear transition plan toward local ownership and control?
A109: Response:
A110: 3. Does the program respect and build upon national health priorities?
A111: Response:
A112: EVIDENCE
A113: Evidence Type:
...

Sheet Input_Integrity
A1: SOLIDARITY INTEGRITY & RISK ASSESSMENT
A2: Section 3: Cross-Cutting Checks to Identify Solidarity Gaps & Contradictions
A4: 1. ALIGNMENT CHECK
A5: Question | B5: Response | C5: Explanation (if applicable)
A6: Are there contradictions between program goals and other activities of the organisation? | B6: No
A7: Does the funder's portfolio include activities that undermine the program's solidarity aims? | B7: No
A8: Is there alignment between stated values and actual resource allocation? | B8: Partially
A10: 2. COST & BURDEN DISTRIBUTION
A11: Question
A12: Who bears the primary burden of implementation costs? | B12: Funder primarily
A13: Are transaction costs (reporting, compliance) proportionate? | B13: No - excessive
A14: Is there evidence of cost-shifting to local actors? | B14: No
A15: Are indirect costs adequately covered? | B15: Partial
A17: 3. VOICE & DECISION-MAKING REALITY
A18: Question
A19: What is the actual level of community involvement in decisions? | B19: Informed only
A20: Can community actors veto or substantially modify program design? | B20: No
A21: Are there formal mechanisms for grievance and feedback? | B21: Not clear
A22: Has community input resulted in actual program changes? | B22: Yes - Some | C22: CHIPS program and community-led initiatives reflect community input
A24: 4. TYPE OF SOLIDARITY OBSERVED
A25: Type | B25: Select | C25: Description | D25: Evidence
A26: Symbolic / Rhetorical | B26: Primary
A27: Partial / Instrumental | B27: Secondary
A28: Substantive / Relational | B28: Primary
A29: Transformative | B29: Secondary
A31: 5. OVERALL INTEGRITY ASSESSMENT
A32: Risk Area | B32: Risk Level (Low/Med/High) | C32: Explanation
A33: Solidarity Washing Risk | B33: High
A34: Power Imbalance Risk | B34: High
A35: Sustainability Risk | B35: Med
A36: Inclusion Gap Risk | B36: Med

Sheet Reference
A1: SOLIDARITY PROFILE ASSESSMENT - REFERENCE GUIDE
A3: FRAMEWORK OVERVIEW
A4: Purpose: | B4: This tool operationalizes the Solidarity Profiling Framework developed through the Global Health Solidarity Project, translating pluriversal solidarity principles into a multidimensional profiling methodology.
A5: Approach: | B5: Non-reductive qualitative profiling capturing orientation (WHAT), process (HOW), and outcomes (TO WHAT END). Generates a solidarity PROFILE, not a composite index or ranking.
A6: Users: | B6: Funders, Program Analysts/Managers, Government Entities, Researchers
A8: THE THREE DIMENSIONS
A9: Dimension | B9: Code | C9: Focus | D9: Domains
A10: WHAT (Orientation) | B10: WHAT | C10: What values and principles guide the program? | D10: D1-D3
A11: HOW (Process) | B11: HOW | C11: How is the program designed and implemented? | D11: D4-D6
A12: TO WHAT END (Outcomes) | B12: END | C12: What outcomes and impacts does it seek? | D12: D7-D9
A14: METHODOLOGICAL FOUNDATION
A15: The framework follows a four-stage translational process:
A16: Stage | B16: Description | C16: Key Features
A17: 1. Domain Mapping | B17: Empirically derived solidarity principles mapped into analytical domains | C17: Reflects nature, enactment, and outcomes of solidarity
A18: 2. Indicator Development | B18: Context-sensitive analytical prompts derived from solidaristic practices | C18: Multiple legitimate expressions coexist; treats reasoned dissent as evidentiary input
A19: 3. Profile Construction | B19: Multidimensional assessment through structured qualitative ratings | C19: Narrative interpretation over composite numerical scores
A20: 4. Deliberative Application | B20: Stakeholders collectively interpret domain-specific findings | C20: Embeds reflexivity, transparency, and shared interpretation
A22: PLURIVERSAL SAFEGUARDS
A23: Safeguard | B23: Purpose | C23: Implementation
A24: Human Rights Floor | B24: Prevents ethical relativism | C24: All interpretations anchored to human rights standards
A25: Anti-Capture Mechanisms | B25: Prevents deliberative capture by elites | C25: Structured representation of marginalized voices
A26: Evidentiary Documentation | B26: Ensures transparency | C26: Clear documentation of evidence supporting each rating
A27: Procedural Justice | B27: Ensures fair participation | C27: Explicit criteria for who contributes to deliberative interpretation
A28: Reflexivity Safeguards | B28: Prevents reductionism | C28: Continuous interrogation of how context shapes inquiry
A30: THEORETICAL GROUNDING
A31: Concept | B31: Source | C31: Application in Framework
A32: Three-Tier Solidarity Model | B32: Prainsack & Buyx (2012) | C32: Interpersonal, communal, and contractual/legal levels of solidarity enactment
A33: Epistemic Justice | B33: Pratt & Vries (2023) | C33: Fairness in distribution of epistemic labour and credence across participants
A34: Pluriversal Theory | B34: Baquero et al. (2021); Barreto (2014) | C34: Recognizes multiple legitimate worldviews without imposing universal metrics
A35: Spidergram Visualization | B35: Rifkin et al.; Baatiema et al. (2013) | C35: Non-numerical comparative representations sustaining interpretive analysis
A37: SOLIDARITY TYPES (After Assessment)
A38: Type | B38: Characteristics | C38: Indicators
A39: Symbolic/Rhetorical | B39: Solidarity language without substantive action | C39: High stated commitment, low resource allocation to solidaristic practices
A40: Partial/Instrumental | B40: Solidarity as means to other ends | C40: Service delivery focus, power structures largely unchanged
A41: Substantive/Relational | B41: Genuine mutual commitment and partnership | C41: Shared decision-making, equitable resource distribution
A42: Transformative | B42: Active dismantling of inequitable structures | C42: Power transformation, systemic change, local sovereignty strengthened
A44: ACKNOWLEDGED LIMITATIONS
A45: Limitation | B45: Implication | C45: Mitigation Strategy
A46: Deliberative capture risk | B46: Power asymmetries may persist despite facilitation | C46: Anti-capture safeguards, structured marginalized voice representation
A47: Subjectivity in interpretation | B47: Context-dependent indicators require judgment | C47: Reflexive safeguards, evidentiary documentation, multiple assessors
A48: Participatory fatigue | B48: Repeated engagement may burden stakeholders | C48: Adequate resourcing, strategic timing of assessments
A49: Limited cross-case comparability | B49: Contextual sensitivity precludes universal ranking | C49: Accept as design feature, not limitation; use for learning not ranking
A50: No empirical field testing | B50: Operational feasibility not yet established | C50: Subsequent validation studies planned
A55: HOW TO USE THIS TOOL
A56: Step 1: | B56: Complete Input_Context sheet with program details
A57: Step 2: | B57: For each domain in Input_Domains, provide rating, responses to prompts, evidence, and confidence
A58: Step 3: | B58: Complete Input_Integrity sheet to identify risks and solidarity type
A59: Step 4: | B59: Review Dashboard for synthesized results and insights
A60: Step 5: | B60: Use narrative summary and decision support for reporting and decision-making
A62: INTERPRETATION GUIDANCE
A63: Pattern | B63: Interpretation | C63: Recommendation
A64: High WHAT, Low HOW | B64: Strong values but weak implementation | C64: Focus on power-sharing and participation mechanisms
A65: High HOW, Low END | B65: Good process but limited impact | C65: Strengthen sustainability and transformation focus
A66: Uneven domain ratings | B66: Inconsistent solidarity expression | C66: Address specific weak domains
A67: Low confidence overall | B67: Assessment needs strengthening | C67: Gather more evidence before conclusions
A68: High risk flags | B68: Potential solidarity gaps | C68: Investigate contradictions and address root causes
A70: IMPORTANT NOTES
A71: • This tool generates a PROFILE, not a score. Avoid reducing results to a single number.
A72: • Context matters: Programs should be assessed within their specific circumstances.
A73: • The tool reveals tensions and contradictions - these are valuable insights, not failures.
A74: • Evidence quality affects reliability - flag low confidence areas in reporting.
A75: • Use for learning and improvement, not just judgment or ranking.

Sheet Calculations
A1: CALCULATIONS - DATA PROCESSING LAYER
A2: This sheet extracts and processes data from input sheets for the Dashboard
A4: DOMAIN RATINGS EXTRACTION
A5: Domain | B5: Code | C5: Dimension | D5: Rating | E5: Confidence | F5: Conf_Value
A6: D1: Equity & Justice | B6: D1 | C6: WHAT | D6: =Input_Domains!B6 -> 3 | E6: =Input_Domains!B18 -> Medium | F6: =IF(E6="High",3,IF(E6="Medium",2,IF(E6="Low",1,0))) -> 2
A7: D2: Common Good Orientation | B7: D2 | C7: WHAT | D7: =Input_Domains!B21 -> 0 | E7: =Input_Domains!B34 -> High | F7: =IF(E7="High",3,IF(E7="Medium",2,IF(E7="Low",1,0))) -> 3
A8: D3: Mutual Responsibility | B8: D3 | C8: WHAT | D8: =Input_Domains!B37 -> 0 | E8: =Input_Domains!B50 -> 0 | F8: =IF(E8="High",3,IF(E8="Medium",2,IF(E8="Low",1,0))) -> 0
A9: D4: Power Transformation | B9: D4 | C9: HOW | D9: =Input_Domains!B54 -> 2 | E9: =Input_Domains!B69 -> High | F9: =IF(E9="High",3,IF(E9="Medium",2,IF(E9="Low",1,0))) -> 3
A10: D5: Inclusive Participation | B10: D5 | C10: HOW | D10: =Input_Domains!B72 -> 1 | E10: =Input_Domains!B85 -> Medium | F10: =IF(E10="High",3,IF(E10="Medium",2,IF(E10="Low",1,0))) -> 2
A11: D6: Transparency & Accountability | B11: D6 | C11: HOW | D11: =Input_Domains!B88 -> 2 | E11: =Input_Domains!B101 -> High | F11: =IF(E11="High",3,IF(E11="Medium",2,IF(E11="Low",1,0))) -> 3
A12: D7: Sustainability & Sovereignty | B12: D7 | C12: END | D12: =Input_Domains!B104 -> 2 | E12: =Input_Domains!B117 -> High | F12: =IF(E12="High",3,IF(E12="Medium",2,IF(E12="Low",1,0))) -> 3
A13: D8: Relational Trust | B13: D8 | C13: END | D13: =Input_Domains!B120 -> 2 | E13: =Input_Domains!B133 -> Medium | F13: =IF(E13="High",3,IF(E13="Medium",2,IF(E13="Low",1,0))) -> 2
A14: D9: Transformative Impact | B14: D9 | C14: END | D14: =Input_Domains!B136 -> 4 | E14: =Input_Domains!B148 -> Medium | F14: =IF(E14="High",3,IF(E14="Medium",2,IF(E14="Low",1,0))) -> 2
A17: DIMENSION AGGREGATIONS
A18: Dimension | B18: Avg Rating | C18: Rating Level | D18: Avg Confidence | E18: Domains Assessed
A19: WHAT (Orientation) | B19: =AVERAGE(D6:D8) -> 1 | C19: =IF(B19>=4,"Strong",IF(B19>=3,"Moderate",IF(B19>=2,"Partial","Emerging"))) -> Emerging | D19: =AVERAGE(F6:F8) -> 1.6666667 | E19: =COUNTIF(C6:C14,"WHAT") -> 3
A20: HOW (Process) | B20: =AVERAGE(D9:D11) -> 1.6666667 | C20: =IF(B20>=4,"Strong",IF(B20>=3,"Moderate",IF(B20>=2,"Partial","Emerging"))) -> Emerging | D20: =AVERAGE(F9:F11) -> 2.6666667 | E20: =COUNTIF(C6:C14,"HOW") -> 3
A21: TO WHAT END (Outcomes) | B21: =AVERAGE(D12:D14) -> 2.6666667 | C21: =IF(B21>=4,"Strong",IF(B21>=3,"Moderate",IF(B21>=2,"Partial","Emerging"))) -> Partial | D21: =AVERAGE(F12:F14) -> 2.3333333 | E21: =COUNTIF(C6:C14,"END") -> 3
A24: OVERALL METRICS
A25: Metric | B25: Value
A26: Overall Average Rating | B26: =AVERAGE(D6:D14) -> 1.7777778
A27: Domains Assessed | B27: =COUNTA(D6:D14)-COUNTBLANK(D6:D14) -> 9
A28: Average Confidence | B28: =AVERAGE(F6:F14) -> 2.2222222
A29: Lowest Domain Rating | B29: =MIN(D6:D14) -> 0
A30: Highest Domain Rating | B30: =MAX(D6:D14) -> 4
A33: INTEGRITY RISK EXTRACTION
A34: Risk Area | B34: Risk Level | C34: Risk Value
A35: Solidarity Washing Risk | B35: =Input_Integrity!B33 -> High | C35: =IF(B35="High",3,IF(B35="Med",2,IF(B35="Low",1,0))) -> 3
A36: Power Imbalance Risk | B36: =Input_Integrity!B34 -> High | C36: =IF(B36="High",3,IF(B36="Med",2,IF(B36="Low",1,0))) -> 3
A37: Sustainability Risk | B37: =Input_Integrity!B35 -> Med | C37: =IF(B37="High",3,IF(B37="Med",2,IF(B37="Low",1,0))) -> 2
A38: Inclusion Gap Risk | B38: =Input_Integrity!B36 -> Med | C38: =IF(B38="High",3,IF(B38="Med",2,IF(B38="Low",1,0))) -> 2
A41: SOLIDARITY TYPE IDENTIFICATION
A42: Type | B42: Selected
A43: Symbolic / Rhetorical | B43: =Input_Integrity!B26 -> Primary
A44: Partial / Instrumental | B44: =Input_Integrity!B27 -> Secondary
A45: Substantive / Relational | B45: =Input_Integrity!B28 -> Primary
A46: Transformative | B46: =Input_Integrity!B29 -> Secondary
A49: PROGRAM CONTEXT EXTRACTION
A50: Field | B50: Value
A51: Program Name | B51: =Input_Context!B6 -> PEPFAR Nigeria
A52: Organisation | B52: =Input_Context!B7 -> USG
A53: Country/Region | B53: =Input_Context!B8 -> Nigeria
A54: Sector | B54: =Input_Context!B9 -> Health - HIV Program
A55: Program Type | B55: =Input_Context!B26 -> 0
A56: Scale | B56: =Input_Context!B28 -> 0
A57: Assessment Date | B57: =Input_Context!B12 -> 0
A58: Assessor | B58: =Input_Context!B13 -> 0
